analytic_workbench_clients/__init__.py
analytic_workbench_clients/cache_store_client.py
analytic_workbench_clients/job_client.py
analytic_workbench_clients/methods_client.py
analytic_workbench_clients/models.py
analytic_workbench_clients/resource_client.py
analytic_workbench_clients-0.7.0.dist-info/LICENSE.txt
analytic_workbench_clients-0.7.0.dist-info/METADATA
analytic_workbench_clients-0.7.0.dist-info/WHEEL
analytic_workbench_clients-0.7.0.dist-info/top_level.txt
analytic_workbench_clients-0.7.0.dist-info/RECORD
